moexalgo/__init__.py
moexalgo/__version__.py
moexalgo/candles.py
moexalgo/currency.py
moexalgo/futures.py
moexalgo/indices.py
moexalgo/market.py
moexalgo/metrics.py
moexalgo/requests.py
moexalgo/session.py
moexalgo/stocks.py
moexalgo/tickers.py
moexalgo/trades.py
moexalgo/utils.py
moexalgo/ahdata/__init__.py
moexalgo/ahdata/client.py
moexalgo/ahdata/models.py
moexalgo/beta/issplus.py
moexalgo/models/__init__.py
moexalgo/models/common.py
moexalgo/models/indices.py
moexalgo/models/metrics.py
moexalgo/models/shares.py
moexalgo/next/__init__.py
moexalgo/next/protocols.py
moexalgo/next/engines/__init__.py
moexalgo/next/engines/_common.py
moexalgo/next/engines/currency.py
moexalgo/next/engines/futures.py
moexalgo/next/engines/stock.py
moexalgo/tools/__init__.py
moexalgo/tools/resample.py
moexalgo-2.4.1.dist-info/METADATA
moexalgo-2.4.1.dist-info/WHEEL
moexalgo-2.4.1.dist-info/top_level.txt
moexalgo-2.4.1.dist-info/RECORD
