Metadata-Version: 2.4
Name: moexalgo
Version: 2.4.1
Summary: Python lib for MOEX AlgoPack data
Classifier: Development Status :: 4 - Beta
Classifier: Programming Language :: Python
Classifier: License :: OSI Approved :: Apache Software License
Classifier: Intended Audience :: Financial and Insurance Industry
Requires-Python: >=3.10
Requires-Dist: httpx
Provides-Extra: pandas
Requires-Dist: pandas>=1.4.1; extra == "pandas"
Requires-Dist: numpy>=1.26.4; extra == "pandas"
Provides-Extra: issplus
Requires-Dist: websockets; extra == "issplus"
Requires-Dist: stomp.py; extra == "issplus"
